MANIFEST.in
README.md
requirements.txt
setup.py
settmhc/MHC_pseudo.dat
settmhc/__init__.py
settmhc/cnn_model.py
settmhc/fusion_model.py
settmhc/hparams.yaml
settmhc/preprocess.py
settmhc/pshm.py
settmhc/rnn_model.py
settmhc/settmhc_main.py
settmhc/structure_modeling.py
settmhc/supported_alleles.txt
settmhc/templates.txt
settmhc/utils.py
settmhc.egg-info/PKG-INFO
settmhc.egg-info/SOURCES.txt
settmhc.egg-info/dependency_links.txt
settmhc.egg-info/entry_points.txt
settmhc.egg-info/requires.txt
settmhc.egg-info/top_level.txt
settmhc/APE-Gen/APE_Gen.py
settmhc/APE-Gen/APE_Gen_IO.py
settmhc/APE-Gen/README.md
settmhc/APE-Gen/__init__.py
settmhc/APE-Gen/align.py
settmhc/APE-Gen/dunbrack.bin
settmhc/APE-Gen/example.ipynb
settmhc/APE-Gen/flex_res.txt
settmhc/APE-Gen/flex_res.txt.orig
settmhc/APE-Gen/get_pMHC_pdb.py
settmhc/APE-Gen/loco.score
settmhc/APE-Gen/minimize.py
settmhc/APE-Gen/model_receptor.py
settmhc/APE-Gen/mutate.py
settmhc/APE-Gen/n-mer-templates.txt
settmhc/APE-Gen/receptor-class-templates.backup.txt
settmhc/APE-Gen/receptor-class-templates.txt
settmhc/APE-Gen/rename_atoms.py
settmhc/APE-Gen/supertype_templates.csv
settmhc/APE-Gen/templates/1DUZ.pdb
settmhc/APE-Gen/templates/1LP9.pdb
settmhc/APE-Gen/templates/1N2R.pdb
settmhc/APE-Gen/templates/1i4f.pdb
settmhc/APE-Gen/templates/1xh3.pdb
settmhc/APE-Gen/templates/2RFX.pdb
settmhc/APE-Gen/templates/2XPG.pdb
settmhc/APE-Gen/templates/2YPL.pdb
settmhc/APE-Gen/templates/2ak4.pdb
settmhc/APE-Gen/templates/2nw3.pdb
settmhc/APE-Gen/templates/2vaa.pdb
settmhc/APE-Gen/templates/3BO8.pdb
settmhc/APE-Gen/templates/3I6L.pdb
settmhc/APE-Gen/templates/3OX8.pdb
settmhc/APE-Gen/templates/3OXS.pdb
settmhc/APE-Gen/templates/3WL9.pdb
settmhc/APE-Gen/templates/3bw9.pdb
settmhc/APE-Gen/templates/3vfv.pdb
settmhc/APE-Gen/templates/4MJI.pdb
settmhc/APE-Gen/templates/4NT6.pdb
settmhc/APE-Gen/templates/4no0.pdb
settmhc/APE-Gen/templates/4u6y.pdb
settmhc/APE-Gen/templates/5BRZ.pdb
settmhc/APE-Gen/templates/5WJN.pdb
settmhc/APE-Gen/templates/5XOT.pdb
settmhc/APE-Gen/templates/5XOV.pdb
settmhc/APE-Gen/templates/5ddh.pdb
settmhc/APE-Gen/templates/5wwi.pdb
settmhc/APE-Gen/templates/A0101.pdb
