Metadata-Version: 2.1
Name: settmhc
Version: 1.0.0
Summary: A peptide-MHC binding predictor based on sequence-structure information
Home-page: UNKNOWN
Author: Chen Wenfan
Author-email: wenfanchan@zju.edu.cn
License: UNKNOWN
Platform: UNKNOWN
